statechartx/__init__.py
statechartx/example.py
statechartx/statechartx.py
statechartx-0.0.2.dist-info/LICENSE
statechartx-0.0.2.dist-info/METADATA
statechartx-0.0.2.dist-info/WHEEL
statechartx-0.0.2.dist-info/top_level.txt
statechartx-0.0.2.dist-info/RECORD
