Metadata-Version: 2.1
Name: statechartx
Version: 0.0.2
Summary: A trivial extension to Python UML statechart framework
Home-page: https://github.com/panuph/statechartx
Author: Panu P
Author-email: panuph@gmail.com
License: UNKNOWN
Platform: UNKNOWN
Classifier: Programming Language :: Python :: 3
Classifier: License :: OSI Approved :: MIT License
